timestring/Date.py
timestring/Range.py
timestring/__init__.py
timestring/timestring_re.py
timestring/utils.py
timestring_pleasantone-1.8.1.dist-info/DESCRIPTION.rst
timestring_pleasantone-1.8.1.dist-info/METADATA
timestring_pleasantone-1.8.1.dist-info/RECORD
timestring_pleasantone-1.8.1.dist-info/WHEEL
timestring_pleasantone-1.8.1.dist-info/entry_points.txt
timestring_pleasantone-1.8.1.dist-info/metadata.json
timestring_pleasantone-1.8.1.dist-info/top_level.txt
timestring_pleasantone-1.8.1.dist-info/zip-safe
